python_agency/__init__.py
python_agency/agent.py
python_agency/agents/__init__.py
python_agency/agents/chattyai.py
python_agency/agents/demo_agent.py
python_agency/agents/host.py
python_agency/agents/prompt_methods.py
python_agency/schema.py
python_agency/space.py
python_agency/spaces/__init__.py
python_agency/spaces/templates/index.html
python_agency/spaces/web_app.py
python_agency/util.py
python_agency-0.1.2.dist-info/LICENSE
python_agency-0.1.2.dist-info/METADATA
python_agency-0.1.2.dist-info/WHEEL
python_agency-0.1.2.dist-info/RECORD
