Metadata-Version: 2.1
Name: python-agency
Version: 0.1.2
Summary: A fast and minimal foundation for unifying human, AI, and other computing systems, in python
License: GPL-3.0
Author: Daniel Rodriguez
Requires-Python: >=3.9,<4.0
Classifier: License :: OSI Approved :: GNU General Public License v3 (GPLv3)
Classifier: Programming Language :: Python :: 3
Classifier: Programming Language :: Python :: 3.9
Classifier: Programming Language :: Python :: 3.10
Classifier: Programming Language :: Python :: 3.11
Requires-Dist: Flask-SocketIO (>=5.3,<6.0)
Requires-Dist: asyncio (>=3.4,<4.0)
Requires-Dist: colorama (>=0.4,<0.5)
Requires-Dist: eventlet (>=0.33,<0.34)
Requires-Dist: openai (>=0.27.8,<0.28.0)
Requires-Dist: pydantic (>=1.8,<2.0)
Requires-Dist: torch (>=2.0,<3.0)
Requires-Dist: transformers (>=4.29,<5.0)
